{
  "robot_id": "packy",
  "HZ": 20,
  "image_resize": {
    "width": 640,
    "height": 240
  },
  "camera_names": [
    "head",
    "left",
    "right"
  ],
  "topics": {
    "finger": {
      "topic": "/igris_b/packy/finger_state",
      "msg_type": "Float32MultiArray",
      "fields": {
        "/observation/hand_joint_pos/left": {
          "slice": [
            6,
            12
          ]
        },
        "/observation/hand_joint_pos/right": {
          "slice": [
            0,
            6
          ]
        }
      }
    },
    "finger_current": {
      "topic": "/igris_b/packy/finger_current",
      "msg_type": "Float32MultiArray",
      "fields": {
        "/observation/hand_joint_cur/left": {
          "slice": [
            6,
            12
          ]
        },
        "/observation/hand_joint_cur/right": {
          "slice": [
            0,
            6
          ]
        }
      }
    },
    "joints": {
      "topic": "/igris_b/packy/joint_states",
      "msg_type": "JointState",
      "fields": {
        "/observation/joint_pos/left": {
          "slice": [
            6,
            12
          ],
          "attr": "position"
        },
        "/observation/joint_pos/right": {
          "slice": [
            0,
            6
          ],
          "attr": "position"
        },
        "/observation/joint_cur/left": {
          "slice": [
            6,
            12
          ],
          "attr": "effort"
        },
        "/observation/joint_cur/right": {
          "slice": [
            0,
            6
          ],
          "attr": "effort"
        }
      }
    }
  },
  "inference": {
    "max_delta": 10.0,
    "image_obs_every": 1,
    "sequential": {
      "max_timesteps": 9000,
      "temporal_ensemble": false,
      "esb_k": 0.01,
      "policy_update_period": 40
    }
  }
}
